setup.py
pythontimer/main.py
pytimer_sao.egg-info/PKG-INFO
pytimer_sao.egg-info/SOURCES.txt
pytimer_sao.egg-info/dependency_links.txt
pytimer_sao.egg-info/not-zip-safe
pytimer_sao.egg-info/top_level.txt